32-bit-alu/q1/oneBitHalfAdder.v
module oneBitHalfAdder(a,b,sum,carry);
    input a, b;
    output sum, carry;
    xor x1(sum, a, b);
    and a1(carry, a, b);
endmodule

32-bit-alu/q1/oneBitAdder.v
`include "oneBitHalfAdder.v"

module oneBitAdder(a, b, cin, sum, cout);
    input a, b, cin;
    output sum, cout;
    wire sum_half, carry_half, carry_half_2;

    oneBitHalfAdder ha1(a, b, sum_half, carry_half);
    oneBitHalfAdder ha2(sum_half, cin, sum, carry_half_2);
    or o1(cout, carry_half, carry_half_2);
endmodule

32-bit-alu/q1/oneBitAdder_tb.v
`include "oneBitAdder.v"

module oneBitAdder_tb;
    reg a, b, cin;
    wire sum, cout;

    oneBitAdder add1(a, b, cin, sum, cout);

    initial
        begin
            $dumpfile("oneBitAdder.vcd");
            $dumpvars(0, oneBitAdder_tb);
            cin = 0; a = 0; b = 0; #1
            cin = 0; a = 0; b = 1; #1
            cin = 0; a = 1; b = 0; #1
            cin = 0; a = 1; b = 1; #1
            cin = 1; a = 0; b = 0; #1
            cin = 1; a = 0; b = 1; #1
            cin = 1; a = 1; b = 0; #1
            cin = 1; a = 1; b = 1;
        end
endmodule
//iverilog -o oneBitAdder_tb.vvp oneBitAdder_tb.v
//vvp oneBitAdder_tb.vvp

32-bit-alu/q1/oneBitAdder.vcd
$date
	Wed Mar 27 12:44:20 2024
$end
$version
	Icarus Verilog
$end
$timescale
	1s
$end
$scope module oneBitAdder_tb $end
$var wire 1 ! sum $end
$var wire 1 " cout $end
$var reg 1 # a $end
$var reg 1 $ b $end
$var reg 1 % cin $end
$scope module add1 $end
$var wire 1 # a $end
$var wire 1 $ b $end
$var wire 1 % cin $end
$var wire 1 " cout $end
$var wire 1 & sum_half $end
$var wire 1 ! sum $end
$var wire 1 ' carry_half_2 $end
$var wire 1 ( carry_half $end
$scope module ha1 $end
$var wire 1 # a $end
$var wire 1 $ b $end
$var wire 1 ( carry $end
$var wire 1 & sum $end
$upscope $end
$scope module ha2 $end
$var wire 1 & a $end
$var wire 1 % b $end
$var wire 1 ' carry $end
$var wire 1 ! sum $end
$upscope $end
$upscope $end
$upscope $end
$enddefinitions $end
$comment Show the parameter values. $end
$dumpall
$end
#0
$dumpvars
0(
0'
0&
0%
0$
0#
0"
0!
$end
#1
1!
1&
1#
#2
0#
1$
#3
0!
1"
0&
1(
1#
#4
0"
0(
1!
0#
0$
1%
#5
1"
0!
1'
1&
1#
#6
0#
1$
#7
1!
0'
0&
1(
1#
